xtest_sapnwrfc/__init__.py
xtest_sapnwrfc/_cyrfc.cpython-311-darwin.so
xtest_sapnwrfc/_exception.py
xtest_sapnwrfc/_utils.py
xtest_sapnwrfc-0.0.17.dist-info/Apache-2.0.txt
xtest_sapnwrfc-0.0.17.dist-info/METADATA
xtest_sapnwrfc-0.0.17.dist-info/WHEEL
xtest_sapnwrfc-0.0.17.dist-info/top_level.txt
xtest_sapnwrfc-0.0.17.dist-info/RECORD
